pictures/__init__.py
pictures/_version.py
pictures/apps.py
pictures/checks.py
pictures/conf.py
pictures/migrations.py
pictures/models.py
pictures/tasks.py
pictures/urls.py
pictures/utils.py
pictures/validators.py
pictures/views.py
pictures/contrib/__init__.py
pictures/contrib/rest_framework.py
pictures/locale/de/LC_MESSAGES/django.po
pictures/templates/pictures/attrs.html
pictures/templates/pictures/picture.html
pictures/templatetags/__init__.py
pictures/templatetags/pictures.py
django_pictures-1.7.1.dist-info/licenses/LICENSE
django_pictures-1.7.1.dist-info/WHEEL
django_pictures-1.7.1.dist-info/METADATA
django_pictures-1.7.1.dist-info/RECORD
