Metadata-Version: 2.4
Name: django-pictures
Version: 1.7.1
Summary: Responsive cross-browser image library using modern codes like AVIF & WebP.
Keywords: pillow,Django,image,pictures,WebP,AVIF
Author-email: Johannes Maron <johannes@maron.family>
Requires-Python: >=3.10
Classifier: Development Status :: 5 - Production/Stable
Classifier: Programming Language :: Python
Classifier: Environment :: Web Environment
Classifier: Topic :: Multimedia :: Graphics :: Graphics Conversion
Classifier: Intended Audience :: Developers
Classifier: License :: OSI Approved :: BSD License
Classifier: Operating System :: OS Independent
Classifier: Programming Language :: Python
Classifier: Topic :: Software Development
Classifier: Programming Language :: Python :: 3
Classifier: Programming Language :: Python :: 3 :: Only
Classifier: Programming Language :: Python :: 3.10
Classifier: Programming Language :: Python :: 3.11
Classifier: Programming Language :: Python :: 3.12
Classifier: Programming Language :: Python :: 3.13
Classifier: Programming Language :: Python :: 3.14
Classifier: Framework :: Django
Classifier: Framework :: Django :: 4.2
Classifier: Framework :: Django :: 5.2
Classifier: Framework :: Django :: 6.0
License-File: LICENSE
Requires-Dist: django>=4.2.0
Requires-Dist: pillow>=11.3.0
Requires-Dist: celery ; extra == "celery"
Requires-Dist: django-cleanup ; extra == "cleanup"
Requires-Dist: django-rq ; extra == "django-rq"
Requires-Dist: dramatiq ; extra == "dramatiq"
Requires-Dist: django-dramatiq ; extra == "dramatiq"
Requires-Dist: djangorestframework ; extra == "drf"
Requires-Dist: pytest ; extra == "test"
Requires-Dist: pytest-cov ; extra == "test"
Requires-Dist: pytest-django ; extra == "test"
Requires-Dist: redis ; extra == "test"
Project-URL: Changelog, https://github.com/codingjoe/django-pictures/releases
Project-URL: Documentation, https://github.com/codingjoe/django-pictures#django-pictures
Project-URL: Issue-Tracker, https://github.com/codingjoe/django-pictures/issues
Project-URL: Project-URL, https://github.com/codingjoe/django-pictures
Project-URL: Source, https://github.com/codingjoe/django-pictures
Provides-Extra: celery
Provides-Extra: cleanup
Provides-Extra: django-rq
Provides-Extra: dramatiq
Provides-Extra: drf
Provides-Extra: test
